{
  "minecraft:recipes/decorations/crafting_table": {
    "criteria": {
      "unlock_right_away": "2025-06-17 01:20:58 +0000"
    },
    "done": true
  },
  "minecraft:adventure/adventuring_time": {
    "criteria": {
      "minecraft:sparse_jungle": "2025-06-17 01:20:59 +0000"
    },
    "done": false
  },
  "minecraft:recipes/building_blocks/jungle_wood": {
    "criteria": {
      "has_log": "2025-06-17 03:55:33 +0000"
    },
    "done": true
  },
  "minecraft:recipes/building_blocks/jungle_planks": {
    "criteria": {
      "has_logs": "2025-06-17 03:55:33 +0000"
    },
    "done": true
  },
  "minecraft:recipes/misc/charcoal": {
    "criteria": {
      "has_log": "2025-06-17 03:55:33 +0000"
    },
    "done": true
  },
  "DataVersion": 3953
}